fenix_library_configuration-0.0.3-py3.9-nspkg.pth
fenix_library/configuration/__init__.py
fenix_library/configuration/configuration.py
fenix_library_configuration-0.0.3.dist-info/LICENSE
fenix_library_configuration-0.0.3.dist-info/METADATA
fenix_library_configuration-0.0.3.dist-info/WHEEL
fenix_library_configuration-0.0.3.dist-info/namespace_packages.txt
fenix_library_configuration-0.0.3.dist-info/top_level.txt
fenix_library_configuration-0.0.3.dist-info/RECORD
