Metadata-Version: 2.1
Name: fenix-library-configuration
Version: 0.0.3
Summary: A library for parsing and storing settings and configurations
Home-page: https://gitlab.com/rebornos-team/fenix/libraries/configuration
Author: Shivanand Pattanshetti
Author-email: shivanandvp@rebornos.org
License: UNKNOWN
Download-URL: https://pypi.org/project/fenix-library-configuration/
Project-URL: Documentation, https://rebornos-team.gitlab.io/fenix/libraries/configuration/
Project-URL: Source, https://gitlab.com/rebornos-team/fenix/libraries/configuration
Project-URL: Tracker, https://gitlab.com/rebornos-team/fenix/libraries/configuration/issues
Platform: UNKNOWN
Classifier: Programming Language :: Python :: 3.9
Classifier: Development Status :: 3 - Alpha
Classifier: License :: OSI Approved :: GNU Affero General Public License v3 or later (AGPLv3+)
Classifier: Operating System :: POSIX :: Linux
Classifier: Intended Audience :: Developers
Classifier: Intended Audience :: System Administrators
Classifier: Natural Language :: English
Classifier: Typing :: Typed
Classifier: Topic :: Software Development :: Libraries :: Python Modules
Classifier: Topic :: System :: Systems Administration
Classifier: Topic :: Utilities
Requires-Python: >=3.6
